{
	"Ag": {
		"id": "Ag",
		"name": "Gross sectional area",
		"description": "Gross cross-sectional area of a member",
		"notation": "A_g",
		"unicode": "A_g",
		"default": "",
		"unit": "mm\u00b2",
		"related": [],
		"docs": "derp ferd",
		"coderef": []
	},
	"alpha2": {
		"id": "alpha2",
		"name": "Alpha2 Coefficient",
		"description": "Coefficient of concrete compressive area in the \"Equivalent compression block method\"",
		"notation": "alpha_2",
		"unicode": "\u03b1\u2082",
		"default": "",
		"unit": "",
		"related": [],
		"docs": "",
		"coderef": []
	},
	"Acc": {
		"id": "Acc",
		"name": "Area of concrete under compression in stress block method",
		"description": "",
		"notation": "A_{cc}",
		"unicode": "A_cc",
		"default": "",
		"unit": "",
		"related": [],
		"docs": "",
		"coderef": []
	},
	"As": {
		"id": "As",
		"name": "Area of reinforcement",
		"description": "cross-sectional area of reinforcement (see Clauses 3.4.3.2 and 13.2.2);",
		"notation": "A_s",
		"unicode": "A_s",
		"default": "",
		"unit": "mm\u00b2",
		"related": [],
		"docs": "",
		"coderef": []
	},
	"Asc": {
		"id": "Asc",
		"name": "Area of compressive steel",
		"description": "cross-sectional area of compressive reinforcement",
		"notation": "A_{sc}",
		"unicode": "A_sc",
		"default": "",
		"unit": "mm\u00b2",
		"related": [],
		"docs": "",
		"coderef": []
	},
	"Ast": {
		"id": "Ast",
		"name": "Area of tensile steel",
		"description": "cross-sectional area of longitudinal tensile reinforcement; or cross-sectional area of reinforcement in the zone that would be in tension under the design loads if the effects of prestress and axial loads are ignored",
		"notation": "A_{st}",
		"unicode": "A_st",
		"default": "",
		"unit": "mm\u00b2",
		"related": [],
		"docs": "",
		"coderef": []
	},
	"b": {
		"id": "b",
		"name": "Breadth of beam",
		"description": "width of a rectangular cross-section or member",
		"notation": "b",
		"unicode": "b",
		"default": 300,
		"unit": "mm",
		"related": [],
		"docs": "",
		"coderef": []
	},
	"Cc": {
		"id": "Cc",
		"name": "Concrete Compression",
		"description": "",
		"notation": "C_c",
		"unicode": "C_c",
		"default": "",
		"unit": "kN",
		"related": [],
		"docs": "",
		"coderef": []
	},
	"d": {
		"id": "d",
		"name": "Depth to tensile steel centroid",
		"description": "effective depth of a cross-section in the plane of bending",
		"notation": "d",
		"unicode": "d",
		"default": "",
		"unit": "mm",
		"related": [],
		"docs": "",
		"coderef": []
	},
	"Depth": {
		"id": "Depth",
		"name": "Depth of beam",
		"description": "overall depth of a cross-section in the plane of bending; or depth or breadth of the symmetrical prism as appropriate (see Clause 12.5.6)",
		"notation": "D",
		"unicode": "D",
		"default": 600,
		"unit": "mm",
		"related": [],
		"docs": "",
		"coderef": []
	},
	"deflim": {
		"id": "deflim",
		"name": "Deflection Limit",
		"description": "",
		"notation": "Delta/L_{ef}",
		"unicode": "\u0394/L_ef",
		"default": "",
		"unit": "",
		"related": [],
		"docs": "",
		"coderef": []
	},
	"dfitments": {
		"id": "dfitments",
		"name": "Diameter of Fitment",
		"description": "",
		"notation": "d_fitments",
		"unicode": "d_fitments",
		"default": 10,
		"unit": "mm",
		"related": [],
		"docs": "",
		"coderef": []
	},
	"dn": {
		"id": "dn",
		"name": "Depth to neutral axis",
		"description": "Depth to neutral axis, measured from the extreme compressive surface of a cross section.",
		"notation": "d_n",
		"unicode": "d_n",
		"default": "",
		"unit": "mm",
		"related": [],
		"docs": "",
		"coderef": []
	},
	"do": {
		"id": "do",
		"name": "Depth to lowest bar",
		"description": "Distance from the extreme compressive fibre of the concrete to the centroid of the outermost layer of tensile reinforcement or tendons (not less than 0.8D for prestressed concrete members)",
		"notation": "d_o",
		"unicode": "d_o",
		"default": "",
		"unit": "",
		"related": [],
		"docs": "",
		"coderef": []
	},
	"Ec": {
		"id": "Ec",
		"name": "Concrete modulus of elasticity",
		"description": "Mean value of the modulus of elasticity of concrete at 28 days",
		"notation": "E_c",
		"unicode": "E_c",
		"default": "",
		"unit": "GPa",
		"related": [],
		"docs": "",
		"coderef": []
	},
	"eclass": {
		"id": "eclass",
		"name": "Exposure Classification",
		"description": "Designation indicative of the most severe environment to which a concrete member is to be subjected during its design life (see Table 4.3).",
		"notation": "",
		"unicode": "",
		"default": "",
		"unit": "",
		"related": [],
		"docs": "",
		"coderef": []
	},
	"epsiloncmax": {
		"id": "epsiloncmax",
		"name": "Maximum concrete strain",
		"description": "Maximum compressive concrete strain",
		"notation": "epsilon_{c max}",
		"unicode": "\u03b5_c_max",
		"default": 0.003,
		"unit": "",
		"related": [],
		"docs": "",
		"coderef": []
	},
	"fc": {
		"id": "fc",
		"name": "Concrete characteristic strength",
		"description": "Characteristic compressive (cylinder) strength of concrete at 28 days",
		"notation": "f'_{c}",
		"unicode": "f'_c",
		"default": 32,
		"unit": "MPa",
		"related": [],
		"docs": "",
		"coderef": []
	},
	"fcm": {
		"id": "fcm",
		"name": "Mean Cylinder Strength",
		"description": "Mean value of cylinder strength (see Clause 3.1.1.2)",
		"notation": "f_{cm}",
		"unicode": "f_cm",
		"default": "",
		"unit": "",
		"related": [],
		"docs": "",
		"coderef": []
	},
	"fcmi": {
		"id": "fcmi",
		"name": "Mean In-situ Strength",
		"description": "Mean value of the in-situ compressive strength of concrete at the relevant age (see Clause 3.1.1.2 and Table 3.1.2)",
		"notation": "f_{cmi}",
		"unicode": "f_cmi",
		"default": "",
		"unit": "",
		"related": [],
		"docs": "",
		"coderef": []
	},
	"fctf": {
		"id": "fctf",
		"name": "Concrete characteristic tensile strength",
		"description": "Measured flexural tensile strength of concrete (see Clause 3.1.1.3)",
		"notation": "f'_{ct.f}",
		"unicode": "f'_ct.f",
		"default": "",
		"unit": "MPa",
		"related": [],
		"docs": "",
		"coderef": []
	},
	"fsy": {
		"id": "fsy",
		"name": "Steel characteristic yield strength",
		"description": "Characteristic yield strength of reinforcement (referred to as Re in AS/NZS 4671), determined in accordance with Clause 3.2.1",
		"notation": "f_{sy}",
		"unicode": "f_sy",
		"default": 500,
		"unit": "MPa",
		"related": [],
		"docs": "",
		"coderef": []
	},
	"gamma": {
		"id": "gamma",
		"name": "Gamma Ratio",
		"description": "Ratio, under design bending or design combined bending and compression, of the depth of the assumed rectangular compressive stress block to k_u * d",
		"notation": "gamma",
		"unicode": "\u03b3",
		"default": "",
		"unit": "",
		"related": [],
		"docs": "",
		"coderef": []
	},
	"I": {
		"id": "I",
		"name": "Second moment of area",
		"description": "Second moment of area of the uncracked concrete cross-section about the centroidal axis",
		"notation": "I",
		"unicode": "I",
		"default": "",
		"unit": "mm\u2074",
		"related": [],
		"docs": "",
		"coderef": []
	},
	"Icr": {
		"id": "Icr",
		"name": "Transformed area second moment of area",
		"description": "Second moment of area of a cracked section with the reinforcement transformed to an equivalent area of concrete",
		"notation": "I_{cr}",
		"unicode": "I_cr",
		"default": "",
		"unit": "mm\u2074",
		"related": [],
		"docs": "",
		"coderef": []
	},
	"Ief": {
		"id": "Ief",
		"name": "Effective second moment of area",
		"description": "Effective second moment of area (see Clause 8.5.3)",
		"notation": "I_{ef}",
		"unicode": "I_ef",
		"default": "",
		"unit": "mm\u2074",
		"related": [],
		"docs": "",
		"coderef": []
	},
	"Iefmax": {
		"id": "Iefmax",
		"name": "Maximum effective second moment of area",
		"description": "Maximum effective second moment of area (see Clause 8.5.3)",
		"notation": "I_{ef.max}",
		"unicode": "I_ef.max",
		"default": "",
		"unit": "mm\u2074",
		"related": [],
		"docs": "",
		"coderef": []
	},
	"ku": {
		"id": "ku",
		"name": "ku Ratio",
		"description": "Neutral axis parameter being the ratio, at ultimate strength under any combination of bending and compression, of the depth to the neutral axis from the extreme compressive fibre to d",
		"notation": "k_u",
		"unicode": "k_u",
		"default": "",
		"unit": "",
		"related": [],
		"docs": "",
		"coderef": []
	},
	"kuo": {
		"id": "kuo",
		"name": "kuo Ratio",
		"description": "Ratio, at ultimate strength, without axial force of the depth to the neutral axis from the extreme compressive fibre to d_o",
		"notation": "k_{uo}",
		"unicode": "k_uo",
		"default": "",
		"unit": "",
		"related": [],
		"docs": "",
		"coderef": []
	},
	"Lef": {
		"id": "Lef",
		"name": "Effective Length",
		"description": "Effective span of a member, taken as the lesser of (Ln + D) and L for a beam or slab; or L_n + D/2 for a cantilever",
		"notation": "L_{ef}",
		"unicode": "L_ef",
		"default": "",
		"unit": "mm",
		"related": [],
		"docs": "",
		"coderef": []
	},
	"Ln": {
		"id": "Ln",
		"name": "Clear Span",
		"description": "Length of clear span in the direction in which moments are being determined, measured face-to-face of supporting beams, columns or walls, or for a cantilever, the clear projection",
		"notation": "L_n",
		"unicode": "L_n",
		"default": 3000,
		"unit": "mm",
		"related": [],
		"docs": "",
		"coderef": []
	},
	"Mo": {
		"id": "Mo",
		"name": "Total Static Moment",
		"description": "Total static moment in a span (see Clause 6.10.4.2); or decompression moment (see Clause 8.2.7.2)",
		"notation": "M_o",
		"unicode": "M_o",
		"default": "",
		"unit": "",
		"related": [],
		"docs": "",
		"coderef": []
	},
	"Mstar": {
		"id": "Mstar",
		"name": "Moment Design Capacity",
		"description": "Design bending moment at a cross-section",
		"notation": "M^*",
		"unicode": "M*",
		"default": "",
		"unit": "kN\u22c5m",
		"related": [],
		"docs": "",
		"coderef": []
	},
	"Mu": {
		"id": "Mu",
		"name": "Moment Ultimate Strength - When combined with axial load",
		"description": "Ultimate strength in bending at a cross-section of an eccentrically loaded compressive member",
		"notation": "M_u",
		"unicode": "M_u",
		"default": "",
		"unit": "",
		"related": [],
		"docs": "",
		"coderef": []
	},
	"Mub": {
		"id": "Mub",
		"name": "Moment Ultimate Strength - When balanced failure occurs",
		"description": "Particular ultimate strength in bending when k_uo = 0.003/(0.003 + f_sy / E_s) (ie. Balanced failure)",
		"notation": "M_{ub}",
		"unicode": "M_ub",
		"default": "",
		"unit": "",
		"related": [],
		"docs": "",
		"coderef": []
	},
	"Muo": {
		"id": "Muo",
		"name": "Moment capacity",
		"description": "Ultimate strength in bending, without axial force, at a cross-section",
		"notation": "M_{uo}",
		"unicode": "M_ou",
		"default": "",
		"unit": "kN\u22c5m",
		"related": [],
		"docs": "",
		"coderef": []
	},
	"Muomin": {
		"id": "Muomin",
		"name": "Minimum design capacity",
		"description": "Minimum required strength in bending at a critical cross-section (see Clause 8.1.6.1)",
		"notation": "(M_{uo})_{min}",
		"unicode": "M_ou_min",
		"default": "",
		"unit": "kN\u22c5m",
		"related": [],
		"docs": "",
		"coderef": []
	},
	"phi": {
		"id": "phi",
		"name": "Capacity reduction factor",
		"description": "Capacity reduction factor for design using linear elastic analysis (see Clause 2.2.2)",
		"notation": "Phi",
		"unicode": "\u03a6",
		"default": "",
		"unit": "",
		"related": [],
		"docs": "",
		"coderef": []
	},
	"reoclass": {
		"id": "reoclass",
		"name": "Reinforcement Ductility Class",
		"description": "AS/NZS 4671 Ductility Class: (L)ow, (N)ormal or (E)arthquake.",
		"notation": "",
		"unicode": "",
		"default": "",
		"unit": "",
		"related": [],
		"docs": "",
		"coderef": []
	},
	"rhoc": {
		"id": "rhoc",
		"name": "Concrete Density",
		"description": "Density of concrete, in kilograms per cubic metre (kg/m3), determined in accordance with Clause 3.1.3",
		"notation": "\rho_c",
		"unicode": "\u03c1_c",
		"default": 2400,
		"unit": "kg/m^3",
		"related": [],
		"docs": "",
		"coderef": []
	},
	"sigmast": {
		"id": "sigmast",
		"name": "Tensile steel stress",
		"description": "Tensile stress in reinforcement (see Clause 13.1.2.4)",
		"notation": "sigma_{st}",
		"unicode": "\u03c3_st",
		"default": "",
		"unit": "",
		"related": [],
		"docs": "",
		"coderef": []
	},
	"Ts": {
		"id": "Ts",
		"name": "Force in tensile steel",
		"description": "Force developed in the portion of tendons which are under tension. Does not include tendons less than half the diameter of the largest tendon.",
		"notation": "T_s",
		"unicode": "T_s",
		"default": "",
		"unit": "kN",
		"related": [],
		"docs": "",
		"coderef": []
	},
	"Z": {
		"id": "Z",
		"name": "Section modulus",
		"description": "Elastic section modulus of the uncracked cross-section, referred to the extreme fibre at which flexural cracking occurs (see Clause 8.1.6.1)",
		"notation": "Z",
		"unicode": "Z",
		"default": "",
		"unit": "mm\u00b3",
		"related": [],
		"docs": "",
		"coderef": []
	},
	"cover": {
		"id": "cover",
		"name": "Cover",
		"description": "Minimum distance between the outer concrete surfaces and the reinforcing bars.",
		"notation": "",
		"unicode": "",
		"default": "",
		"unit": "mm",
		"related": [],
		"docs": "",
		"coderef": []
	},
	"Es": {
		"id": "Es",
		"name": "Reo modulus of elasticity",
		"description": "Young's modulus of elasticity of reinforcement, determined in accordance with Clause 3.2.2",
		"notation": "E_s",
		"unicode": "E_s",
		"default": 200000,
		"unit": "MPa",
		"related": [],
		"docs": "",
		"coderef": []
	}
}